pyiArduinoI2Crelay.cpython-35m-arm-linux-gnueabihf.so
pyiArduinoI2Crelay-1.6.3.dist-info/DESCRIPTION.rst
pyiArduinoI2Crelay-1.6.3.dist-info/METADATA
pyiArduinoI2Crelay-1.6.3.dist-info/RECORD
pyiArduinoI2Crelay-1.6.3.dist-info/WHEEL
pyiArduinoI2Crelay-1.6.3.dist-info/metadata.json
pyiArduinoI2Crelay-1.6.3.dist-info/top_level.txt
