Metadata-Version: 2.0
Name: pyiArduinoI2Crelay
Version: 1.6.3
Summary: iarduino.ru module for Raspberry Pi
Home-page: http://github.com/tremaru/pyiArduinoI2Crelay
Author: iarduino.ru
Author-email: shop@iarduino.ru
License: MIT
Platform: UNKNOWN
Classifier: Programming Language :: Python :: 3
Requires-Python: >=3, <4
